pts_itech_m3905d_psu/__init__.py
pts_itech_m3905d_psu/pts_itech_m3905d_psu.py
pts_itech_m3905d_psu-0.0.2.dist-info/LICENSE.txt
pts_itech_m3905d_psu-0.0.2.dist-info/METADATA
pts_itech_m3905d_psu-0.0.2.dist-info/WHEEL
pts_itech_m3905d_psu-0.0.2.dist-info/top_level.txt
pts_itech_m3905d_psu-0.0.2.dist-info/RECORD
